{
  "version": 1,
  "dependencies": [
    {
      "source": {
        "git": {
          "remote": "https://github.com/grafana/jsonnet-libs.git",
          "subdir": "grafana-builder"
        }
      },
      "version": "2860a02cdd2e44d793e3242e2f0c7c12f0d9113f",
      "sum": "5ku1Hd8UPnjmn8nWyaTFzMpT3Pa+VylBnmposMSVEuU="
    },
    {
      "source": {
        "git": {
          "remote": "https://github.com/grafana/jsonnet-libs.git",
          "subdir": "mixin-utils"
        }
      },
      "version": "2860a02cdd2e44d793e3242e2f0c7c12f0d9113f",
      "sum": "c38fwJCz23fGdD29XgrBI+vCkK+uS3bnOb/z4pDT2Vc="
    }
  ],
  "legacyImports": false
}
