{
  "version": 1,
  "dependencies": [
    {
      "source": {
        "git": {
          "remote": "https://github.com/grafana/jsonnet-libs.git",
          "subdir": "grafana-builder"
        }
      },
      "version": "7561fd330312538d22b00e0c7caecb4ba66321ea",
      "sum": "+z5VY+bPBNqXcmNAV8xbJcbsRA+pro1R3IM7aIY8OlU="
    },
    {
      "source": {
        "git": {
          "remote": "https://github.com/grafana/jsonnet-libs.git",
          "subdir": "mixin-utils"
        }
      },
      "version": "7561fd330312538d22b00e0c7caecb4ba66321ea",
      "sum": "0jg7qc3N8FtMnnQbunYCGSNcjHr9Y1krZW9OSTmWcEQ="
    }
  ],
  "legacyImports": false
}
